spark/__init__.py
spark/admin.py
spark/api.py
spark/apps.py
spark/models.py
spark/locale/de/LC_MESSAGES/django.mo
spark/locale/de/LC_MESSAGES/django.po
spark/management/__init__.py
spark/management/commands/__init__.py
spark/management/commands/process_spark_sources.py
spark/migrations/0001_initial.py
spark/migrations/0002_auto_20171219_1531.py
spark/migrations/__init__.py
spark/spark_generators/__init__.py
spark/spark_generators/admin.py
spark/spark_generators/api.py
spark/spark_generators/apps.py
spark/spark_generators/models.py
spark/spark_generators/migrations/0001_initial.py
spark/spark_generators/migrations/__init__.py
spark/spark_mails/__init__.py
spark/spark_mails/admin.py
spark/spark_mails/api.py
spark/spark_mails/apps.py
spark/spark_mails/models.py
spark/spark_mails/migrations/0001_initial.py
spark/spark_mails/migrations/__init__.py
django_spark-0.3.0.dist-info/LICENSE
django_spark-0.3.0.dist-info/METADATA
django_spark-0.3.0.dist-info/WHEEL
django_spark-0.3.0.dist-info/top_level.txt
django_spark-0.3.0.dist-info/RECORD
