Metadata-Version: 2.1
Name: django-spark
Version: 0.3.0
Summary: Event sourcing and handling
Home-page: http://github.com/matthiask/django-spark/
Author: Matthias Kestenholz
Author-email: mk@feinheit.ch
License: BSD License
Platform: OS Independent
Classifier: Environment :: Web Environment
Classifier: Framework :: Django
Classifier: Intended Audience :: Developers
Classifier: License :: OSI Approved :: BSD License
Classifier: Operating System :: OS Independent
Classifier: Programming Language :: Python
Classifier: Programming Language :: Python :: 3
Classifier: Topic :: Internet :: WWW/HTTP :: Dynamic Content
Classifier: Topic :: Software Development
Classifier: Topic :: Software Development :: Libraries :: Application Frameworks
